english_text_normalization/__init__.py
english_text_normalization/normalization_pipeline.py
english_text_normalization/sentence_extraction.py
english_text_normalization/adjustments/__init__.py
english_text_normalization/adjustments/abbreviations.py
english_text_normalization/adjustments/emails.py
english_text_normalization/adjustments/fraction_normalization.py
english_text_normalization/adjustments/king_names_normalization.py
english_text_normalization/adjustments/layout_normalization.py
english_text_normalization/adjustments/money_normalization.py
english_text_normalization/adjustments/month_normalization.py
english_text_normalization/adjustments/normalization_of_certain_words_and_abbr.py
english_text_normalization/adjustments/normalize_degrees.py
english_text_normalization/adjustments/numbers.py
english_text_normalization/adjustments/other.py
english_text_normalization/adjustments/remove_dots_that_are_not_end_of_sentence.py
english_text_normalization/adjustments/unit_abbreviations_normalization.py
english_text_normalization/adjustments/write_out_special_characters.py
english_text_normalization/auxiliary_methods/__init__.py
english_text_normalization/auxiliary_methods/operations.py
english_text_normalization/auxiliary_methods/roman_numerals.py
english_text_normalization/auxiliary_methods/search_pattern_in_books.py
english_text_normalization/auxiliary_methods/txt_files_reading.py
english_text_normalization/resources/name_corpus.txt
english_text_normalization_cli/__init__.py
english_text_normalization_cli/cli.py
english_text_normalization_cli/file_text_normalization.py
english_text_normalization_cli/folder_text_normalization.py
english_text_normalization_cli/globals.py
english_text_normalization_cli/helper.py
english_text_normalization_cli/logging_configuration.py
english_text_normalization_cli/operations_listing.py
english_text_normalization_tests/__init__.py
english_text_normalization_tests/test_emails.py
english_text_normalization-0.0.3.dist-info/LICENSE
english_text_normalization-0.0.3.dist-info/METADATA
english_text_normalization-0.0.3.dist-info/WHEEL
english_text_normalization-0.0.3.dist-info/entry_points.txt
english_text_normalization-0.0.3.dist-info/top_level.txt
english_text_normalization-0.0.3.dist-info/RECORD
