Metadata-Version: 2.1
Name: english-text-normalization
Version: 0.0.3
Summary: Command-line interface (CLI) and library to normalize English texts.
Author-email: Jasmin Sternkopf <jasmin.sternkopf@mathematik.tu-chemnitz.de>, Stefan Taubert <pypi@stefantaubert.com>
Maintainer-email: Stefan Taubert <pypi@stefantaubert.com>
License: MIT
Project-URL: Homepage, https://github.com/jasminsternkopf/english_text_normalization
Project-URL: Issues, https://github.com/jasminsternkopf/english_text_normalization/issues
Keywords: Text-to-speech,Speech synthesis,Regex,Language,Linguistics
Classifier: Development Status :: 2 - Pre-Alpha
Classifier: Operating System :: OS Independent
Classifier: Operating System :: MacOS
Classifier: Operating System :: POSIX
Classifier: Operating System :: POSIX :: BSD
Classifier: Operating System :: POSIX :: Linux
Classifier: Operating System :: Unix
Classifier: Operating System :: Microsoft :: Windows
Classifier: Programming Language :: Python
Classifier: Programming Language :: Python :: 3
Classifier: Programming Language :: Python :: 3.8
Classifier: Programming Language :: Python :: 3.9
Classifier: Programming Language :: Python :: 3.10
Classifier: Programming Language :: Python :: 3.11
Classifier: Programming Language :: Python :: 3.12
Classifier: License :: OSI Approved :: MIT License
Requires-Python: <3.13,>=3.8
License-File: LICENSE
Requires-Dist: pyenchant
Requires-Dist: nltk
Requires-Dist: inflect
Requires-Dist: unidecode
